[
  {
    "source": "computerfinearts",
    "source_url": "https://web.archive.org/web/20060222031112/http://www.computerfinearts.com/collection/campbell/spawn/",
    "title": "..::..::....:...SPAWN..:::::...:::..::.....",
    "artist": "Alexa Campbell",
    "year": null,
    "url": "http://www.computerfinearts.com/collection/campbell/spawn/",
    "medium": "Net art"
  },
  {
    "source": "computerfinearts",
    "source_url": "https://web.archive.org/web/20060222031447/http://www.computerfinearts.com/collection/campbell/annesykes/",
    "title": "The Diary of Anne Sykes",
    "artist": "Alexa Campbell",
    "year": null,
    "url": "http://www.computerfinearts.com/collection/campbell/annesykes/",
    "medium": "Net art"
  },
  {
    "source": "computerfinearts",
    "source_url": "https://web.archive.org/web/20060222031454/http://www.computerfinearts.com/collection/campbell/fractured/",
    "title": "Fractured",
    "artist": "Alexa Campbell",
    "year": null,
    "url": "http://www.computerfinearts.com/collection/campbell/fractured/",
    "medium": "Net art"
  },
  {
    "source": "computerfinearts",
    "source_url": "https://web.archive.org/web/20060222031435/http://www.computerfinearts.com/collection/campbell/facedown/",
    "title": "|| FACEDOWN ||",
    "artist": "Alexa Campbell",
    "year": null,
    "url": "http://www.computerfinearts.com/collection/campbell/facedown/",
    "medium": "Net art"
  },
  {
    "source": "computerfinearts",
    "source_url": "https://web.archive.org/web/20060222024229/http://www.computerfinearts.com/collection/polli/pause/",
    "title": "opening02",
    "artist": "Andrea Polli",
    "year": null,
    "url": "http://www.computerfinearts.com/collection/polli/pause/",
    "medium": "Net art"
  },
  {
    "source": "computerfinearts",
    "source_url": "https://web.archive.org/web/20060222025846/http://www.computerfinearts.com/collection/decologne/predator/",
    "title": "Predator - moving picture by Agricola de Cologne - \ufffd 2003",
    "artist": "Andreas De Cologne",
    "year": null,
    "url": "http://www.computerfinearts.com/collection/decologne/predator/",
    "medium": "Net art"
  },
  {
    "source": "computerfinearts",
    "source_url": "https://web.archive.org/web/20060222025554/http://www.computerfinearts.com/collection/deck/borderStyle/",
    "title": "Border Style",
    "artist": "Andy Deck",
    "year": null,
    "url": "http://www.computerfinearts.com/collection/deck/borderStyle/",
    "medium": "Net art"
  },
  {
    "source": "computerfinearts",
    "source_url": "https://web.archive.org/web/20021229034356/http://www.computerfinearts.com/collection/deck/MEMORY.MIL/",
    "title": "MEMORY.MIL",
    "artist": "Andy Deck",
    "year": null,
    "url": "http://www.computerfinearts.com/collection/deck/MEMORY.MIL/",
    "medium": "Net art"
  },
  {
    "source": "computerfinearts",
    "source_url": "https://web.archive.org/web/20070825203347/http://www.computerfinearts.com/collection/deck/wildlifeOffline/",
    "title": "Wildlife Offline",
    "artist": "Andy Deck",
    "year": null,
    "url": "http://www.computerfinearts.com/collection/deck/wildlifeOffline/",
    "medium": "Net art"
  },
  {
    "source": "computerfinearts",
    "source_url": "https://web.archive.org/web/20061007124445/http://www.computerfinearts.com/collection/weintraub/mirage/",
    "title": "Mirage",
    "artist": "Annette Weintraub",
    "year": null,
    "url": "http://www.computerfinearts.com/collection/weintraub/mirage/",
    "medium": "Net art"
  },
  {
    "source": "computerfinearts",
    "source_url": "https://web.archive.org/web/20060209030717/http://www.computerfinearts.com/collection/abrahams/happymoving/",
    "title": "happy moving",
    "artist": "Annie Abrahams",
    "year": null,
    "url": "http://www.computerfinearts.com/collection/abrahams/happymoving/",
    "medium": "Net art"
  },
  {
    "source": "computerfinearts",
    "source_url": "https://web.archive.org/web/20061030085803/http://www.computerfinearts.com/collection/abrahams/separation/",
    "title": "Separation / S\u00e9paration",
    "artist": "Annie Abrahams",
    "year": null,
    "url": "http://www.computerfinearts.com/collection/abrahams/separation/",
    "medium": "Net art"
  },
  {
    "source": "computerfinearts",
    "source_url": "https://web.archive.org/web/20060222024953/http://www.computerfinearts.com/collection/mendoza/anime/",
    "title": "G O T . M E T H ?",
    "artist": "Arcangel Mendoza",
    "year": null,
    "url": "http://www.computerfinearts.com/collection/mendoza/anime/",
    "medium": "Net art"
  },
  {
    "source": "computerfinearts",
    "source_url": "https://web.archive.org/web/20060222024959/http://www.computerfinearts.com/collection/mendoza/disco/",
    "title": "s y s t e m . f a i l u r e",
    "artist": "Arcangel Mendoza",
    "year": null,
    "url": "http://www.computerfinearts.com/collection/mendoza/disco/",
    "medium": "Net art"
  },
  {
    "source": "computerfinearts",
    "source_url": "https://web.archive.org/web/20060222025527/http://www.computerfinearts.com/collection/schmitt/thehole/",
    "title": "the hole",
    "artist": "Axel Schmitt",
    "year": null,
    "url": "http://www.computerfinearts.com/collection/schmitt/thehole/",
    "medium": "Net art"
  },
  {
    "source": "computerfinearts",
    "source_url": "https://web.archive.org/web/20060222025917/http://www.computerfinearts.com/collection/schmitt/thewitness/",
    "title": "the witness",
    "artist": "Axel Schmitt",
    "year": null,
    "url": "http://www.computerfinearts.com/collection/schmitt/thewitness/",
    "medium": "Net art"
  },
  {
    "source": "computerfinearts",
    "source_url": "https://web.archive.org/web/20060222052104/http://www.computerfinearts.com/collection/lattanzi/bridgecrossing/",
    "title": "bridge crossing",
    "artist": "Bill Lattanzi",
    "year": null,
    "url": "http://www.computerfinearts.com/collection/lattanzi/bridgecrossing/",
    "medium": "Net art"
  },
  {
    "source": "computerfinearts",
    "source_url": "https://web.archive.org/web/20060222052057/http://www.computerfinearts.com/collection/lattanzi/electrocution/",
    "title": "electrocution, 1901",
    "artist": "Bill Lattanzi",
    "year": null,
    "url": "http://www.computerfinearts.com/collection/lattanzi/electrocution/",
    "medium": "Net art"
  },
  {
    "source": "computerfinearts",
    "source_url": "https://web.archive.org/web/20060222051958/http://www.computerfinearts.com/collection/lattanzi/hearme/",
    "title": "hear me! riff",
    "artist": "Bill Lattanzi",
    "year": null,
    "url": "http://www.computerfinearts.com/collection/lattanzi/hearme/",
    "medium": "Net art"
  },
  {
    "source": "computerfinearts",
    "source_url": "https://web.archive.org/web/20060222051912/http://www.computerfinearts.com/collection/lattanzi/stalker/",
    "title": "stalker",
    "artist": "Bill Lattanzi",
    "year": null,
    "url": "http://www.computerfinearts.com/collection/lattanzi/stalker/",
    "medium": "Net art"
  },
  {
    "source": "computerfinearts",
    "source_url": "https://web.archive.org/web/20060222052011/http://www.computerfinearts.com/collection/lattanzi/startle/",
    "title": "startle",
    "artist": "Bill Lattanzi",
    "year": null,
    "url": "http://www.computerfinearts.com/collection/lattanzi/startle/",
    "medium": "Net art"
  },
  {
    "source": "computerfinearts",
    "source_url": "https://web.archive.org/web/20060222052051/http://www.computerfinearts.com/collection/lattanzi/youarelate/",
    "title": "you are late",
    "artist": "Bill Lattanzi",
    "year": null,
    "url": "http://www.computerfinearts.com/collection/lattanzi/youarelate/",
    "medium": "Net art"
  },
  {
    "source": "computerfinearts",
    "source_url": "https://web.archive.org/web/20070825202855/http://www.computerfinearts.com/collection/boredomresearch/wish/",
    "title": "Wish info",
    "artist": "boredomresearch",
    "year": null,
    "url": "http://www.computerfinearts.com/collection/boredomresearch/wish/",
    "medium": "Net art"
  },
  {
    "source": "computerfinearts",
    "source_url": "https://web.archive.org/web/20061030084915/http://www.computerfinearts.com/collection/todd/hearingloss/",
    "title": "HearingLoss",
    "artist": "Brian Todd",
    "year": null,
    "url": "http://www.computerfinearts.com/collection/todd/hearingloss/",
    "medium": "Net art"
  },
  {
    "source": "computerfinearts",
    "source_url": "https://web.archive.org/web/20070827172614/http://www.computerfinearts.com/collection/zanni/eBayLandscape/",
    "title": "landscapes...",
    "artist": "Carlo Zanni",
    "year": null,
    "url": "http://www.computerfinearts.com/collection/zanni/eBayLandscape/",
    "medium": "Net art"
  },
  {
    "source": "computerfinearts",
    "source_url": "https://web.archive.org/web/20031210135050/http://www.computerfinearts.com/collection/peppermint/mediation/",
    "title": "you ain't gonna believe this one.",
    "artist": "Cary Peppermint",
    "year": null,
    "url": "http://www.computerfinearts.com/collection/peppermint/mediation/",
    "medium": "Net art"
  },
  {
    "source": "computerfinearts",
    "source_url": "https://web.archive.org/web/20060222025548/http://www.computerfinearts.com/collection/coyarzun/wIPhOME/",
    "title": "COYARZUN:/*WIPhOME0701v1.2*/",
    "artist": "Coyarzun",
    "year": null,
    "url": "http://www.computerfinearts.com/collection/coyarzun/wIPhOME/",
    "medium": "Net art"
  },
  {
    "source": "computerfinearts",
    "source_url": "https://web.archive.org/web/20030329185312/http://www.computerfinearts.com/collection/cloninger/rebranding/",
    "title": "REbranding",
    "artist": "Curt Cloninger",
    "year": null,
    "url": "http://www.computerfinearts.com/collection/cloninger/rebranding/",
    "medium": "Net art"
  },
  {
    "source": "computerfinearts",
    "source_url": "https://web.archive.org/web/20040225065146/http://www.computerfinearts.com/collection/cloninger/bubblegum/",
    "title": "sbgc!",
    "artist": "Curt Cloninger",
    "year": null,
    "url": "http://www.computerfinearts.com/collection/cloninger/bubblegum/",
    "medium": "Net art"
  },
  {
    "source": "computerfinearts",
    "source_url": "https://web.archive.org/web/20060222051852/http://www.computerfinearts.com/collection/doctorhugo/dreamz/",
    "title": "Dr. Hugo's Fuzzy Dreamz 00 || Museums of the Mind ||",
    "artist": "Doctor Hugo",
    "year": null,
    "url": "http://www.computerfinearts.com/collection/doctorhugo/dreamz/",
    "medium": "Net art"
  },
  {
    "source": "computerfinearts",
    "source_url": "https://web.archive.org/web/20060222052017/http://www.computerfinearts.com/collection/doctorhugo/dreamz01/",
    "title": "Dr. Hugo's Fuzzy Dreamz 01 || Museums of the Mind ||",
    "artist": "Doctor Hugo",
    "year": null,
    "url": "http://www.computerfinearts.com/collection/doctorhugo/dreamz01/",
    "medium": "Net art"
  },
  {
    "source": "computerfinearts",
    "source_url": "https://web.archive.org/web/20060222052023/http://www.computerfinearts.com/collection/doctorhugo/dreamz02/",
    "title": "Dr. Hugo's Fuzzy Dreamz 02 || Museums of the Mind ||",
    "artist": "Doctor Hugo",
    "year": null,
    "url": "http://www.computerfinearts.com/collection/doctorhugo/dreamz02/",
    "medium": "Net art"
  },
  {
    "source": "computerfinearts",
    "source_url": "https://web.archive.org/web/20060222052033/http://www.computerfinearts.com/collection/doctorhugo/dreamz03/",
    "title": "Dr. Hugo's Fuzzy Dreamz 03 || Museums of the Mind ||",
    "artist": "Doctor Hugo",
    "year": null,
    "url": "http://www.computerfinearts.com/collection/doctorhugo/dreamz03/",
    "medium": "Net art"
  },
  {
    "source": "computerfinearts",
    "source_url": "https://web.archive.org/web/20060222052039/http://www.computerfinearts.com/collection/doctorhugo/dreamz04/",
    "title": "Dr. Hugo's Fuzzy Dreamz 04 || Museums of the Mind ||",
    "artist": "Doctor Hugo",
    "year": null,
    "url": "http://www.computerfinearts.com/collection/doctorhugo/dreamz04/",
    "medium": "Net art"
  },
  {
    "source": "computerfinearts",
    "source_url": "https://web.archive.org/web/20060222052046/http://www.computerfinearts.com/collection/doctorhugo/dreamz05/",
    "title": "Dr. Hugo's Fuzzy Dreamz 05 || Museums of the Mind ||",
    "artist": "Doctor Hugo",
    "year": null,
    "url": "http://www.computerfinearts.com/collection/doctorhugo/dreamz05/",
    "medium": "Net art"
  },
  {
    "source": "computerfinearts",
    "source_url": "https://web.archive.org/web/20021021195434/http://www.computerfinearts.com/collection/easylife.org/xxx/",
    "title": "Xxx",
    "artist": "easylife.org",
    "year": null,
    "url": "http://www.computerfinearts.com/collection/easylife.org/xxx/",
    "medium": "Net art"
  },
  {
    "source": "computerfinearts",
    "source_url": "https://web.archive.org/web/20060222031354/http://www.computerfinearts.com/collection/burton/fields/",
    "title": "fields, ed burton",
    "artist": "Ed Burton",
    "year": null,
    "url": "http://www.computerfinearts.com/collection/burton/fields/",
    "medium": "Net art"
  },
  {
    "source": "computerfinearts",
    "source_url": "https://web.archive.org/web/20060222031359/http://www.computerfinearts.com/collection/burton/stress/",
    "title": "stress, ed burton",
    "artist": "Ed Burton",
    "year": null,
    "url": "http://www.computerfinearts.com/collection/burton/stress/",
    "medium": "Net art"
  },
  {
    "source": "computerfinearts",
    "source_url": "https://web.archive.org/web/20060222031429/http://www.computerfinearts.com/collection/burton/threeforms/",
    "title": "three forms, ed burton",
    "artist": "Ed Burton",
    "year": null,
    "url": "http://www.computerfinearts.com/collection/burton/threeforms/",
    "medium": "Net art"
  },
  {
    "source": "computerfinearts",
    "source_url": "https://web.archive.org/web/20080322122226/http://www.computerfinearts.com/collection/navas/diaryofastar/",
    "title": "star",
    "artist": "Eduardo Navas",
    "year": null,
    "url": "http://www.computerfinearts.com/collection/navas/diaryofastar/",
    "medium": "Net art"
  },
  {
    "source": "computerfinearts",
    "source_url": "https://web.archive.org/web/20060222025600/http://www.computerfinearts.com/collection/dekok/zabnulvier/",
    "title": "zabnulvier v.008 - elout de kok \ufffd2004",
    "artist": "Eelco De Kok",
    "year": null,
    "url": "http://www.computerfinearts.com/collection/dekok/zabnulvier/",
    "medium": "Net art"
  },
  {
    "source": "computerfinearts",
    "source_url": "https://web.archive.org/web/20060222011858/http://www.computerfinearts.com/collection/hovagimyan/vanitysearch/",
    "title": "Vanitysearch",
    "artist": "G.H. Hovagimyan",
    "year": null,
    "url": "http://www.computerfinearts.com/collection/hovagimyan/vanitysearch/",
    "medium": "Net art"
  },
  {
    "source": "computerfinearts",
    "source_url": "https://web.archive.org/web/20080515093000/http://www.computerfinearts.com/collection/geuzen/guy/",
    "title": "A Seance with Guy Debord",
    "artist": "Geuzen",
    "year": null,
    "url": "http://www.computerfinearts.com/collection/geuzen/guy/",
    "medium": "Net art"
  },
  {
    "source": "computerfinearts",
    "source_url": "https://web.archive.org/web/20080515093112/http://www.computerfinearts.com/collection/geuzen/brains/",
    "title": "BRAINS NOT BOMBS",
    "artist": "Geuzen",
    "year": null,
    "url": "http://www.computerfinearts.com/collection/geuzen/brains/",
    "medium": "Net art"
  },
  {
    "source": "computerfinearts",
    "source_url": "https://web.archive.org/web/20060222024030/http://www.computerfinearts.com/collection/levin/putty/",
    "title": "puttypix",
    "artist": "Golan Levin",
    "year": null,
    "url": "http://www.computerfinearts.com/collection/levin/putty/",
    "medium": "Net art"
  },
  {
    "source": "computerfinearts",
    "source_url": "https://web.archive.org/web/20060222030235/http://www.computerfinearts.com/collection/chatonsky/revolution_new_york/",
    "title": "THE REVOLUTION TOOK PLACE IN NEW YORK - GOOGLE NARRATIVE ENGINE - GREGORY CHATONSKY - 2002-2003",
    "artist": "Gregory Chatonsky",
    "year": null,
    "url": "http://www.computerfinearts.com/collection/chatonsky/revolution_new_york/",
    "medium": "Net art"
  },
  {
    "source": "computerfinearts",
    "source_url": "https://web.archive.org/web/20060222031423/http://www.computerfinearts.com/collection/bunting/old_photo/",
    "title": "Old Photo",
    "artist": "Heath Bunting",
    "year": null,
    "url": "http://www.computerfinearts.com/collection/bunting/old_photo/",
    "medium": "Net art"
  },
  {
    "source": "computerfinearts",
    "source_url": "https://web.archive.org/web/20070205001757/http://www.computerfinearts.com/collection/bunting/photo/",
    "title": "Photo",
    "artist": "Heath Bunting",
    "year": null,
    "url": "http://www.computerfinearts.com/collection/bunting/photo/",
    "medium": "Net art"
  },
  {
    "source": "computerfinearts",
    "source_url": "https://web.archive.org/web/20061007123451/http://www.computerfinearts.com/collection/stromajer/gpsart/",
    "title": "Gpsart",
    "artist": "Igor Stromajer",
    "year": null,
    "url": "http://www.computerfinearts.com/collection/stromajer/gpsart/",
    "medium": "Net art"
  },
  {
    "source": "computerfinearts",
    "source_url": "https://web.archive.org/web/20031212153655/http://www.computerfinearts.com/collection/mcelroy/cult/",
    "title": "Cor[porat]e [Per]form[ance] Art[ist]",
    "artist": "J&D McElroy",
    "year": null,
    "url": "http://www.computerfinearts.com/collection/mcelroy/cult/",
    "medium": "Net art"
  },
  {
    "source": "computerfinearts",
    "source_url": "https://web.archive.org/web/20031212153402/http://www.computerfinearts.com/collection/mcelroy/jimmy/",
    "title": "jimmy",
    "artist": "J&D McElroy",
    "year": null,
    "url": "http://www.computerfinearts.com/collection/mcelroy/jimmy/",
    "medium": "Net art"
  },
  {
    "source": "computerfinearts",
    "source_url": "https://web.archive.org/web/20070828173651/http://www.computerfinearts.com/collection/zeleznikar/bela02/",
    "title": "Bela02",
    "artist": "Jaka Zeleznikar",
    "year": null,
    "url": "http://www.computerfinearts.com/collection/zeleznikar/bela02/",
    "medium": "Net art"
  },
  {
    "source": "computerfinearts",
    "source_url": "https://web.archive.org/web/20060222025936/http://www.computerfinearts.com/collection/zeleznikar/echelon/",
    "title": "Poem for Echelon",
    "artist": "Jaka Zeleznikar",
    "year": null,
    "url": "http://www.computerfinearts.com/collection/zeleznikar/echelon/",
    "medium": "Net art"
  },
  {
    "source": "computerfinearts",
    "source_url": "https://web.archive.org/web/20060222031417/http://www.computerfinearts.com/collection/leegte/untitled/",
    "title": "Untitled - Jan Robert Leegte",
    "artist": "Jan Robert Leegte",
    "year": null,
    "url": "http://www.computerfinearts.com/collection/leegte/untitled/",
    "medium": "Net art"
  },
  {
    "source": "computerfinearts",
    "source_url": "https://web.archive.org/web/20060222031153/http://www.computerfinearts.com/collection/leegte/rgb/",
    "title": "Untitled [rgb]",
    "artist": "Jan Robert Leegte",
    "year": null,
    "url": "http://www.computerfinearts.com/collection/leegte/rgb/",
    "medium": "Net art"
  },
  {
    "source": "computerfinearts",
    "source_url": "https://web.archive.org/web/20060222031441/http://www.computerfinearts.com/collection/leegte/scrollbars/",
    "title": "Untitled [scrollbars]",
    "artist": "Jan Robert Leegte",
    "year": null,
    "url": "http://www.computerfinearts.com/collection/leegte/scrollbars/",
    "medium": "Net art"
  },
  {
    "source": "computerfinearts",
    "source_url": "https://web.archive.org/web/20060222030219/http://www.computerfinearts.com/collection/loseby/trivialconnections/",
    "title": "trivial connections jessica loseby 2003",
    "artist": "Jane Loseby",
    "year": null,
    "url": "http://www.computerfinearts.com/collection/loseby/trivialconnections/",
    "medium": "Net art"
  },
  {
    "source": "computerfinearts",
    "source_url": "https://web.archive.org/web/20060222041047/http://www.computerfinearts.com/collection/nelson/ending1/",
    "title": "ending1",
    "artist": "Jason Nelson",
    "year": null,
    "url": "http://www.computerfinearts.com/collection/nelson/ending1/",
    "medium": "Net art"
  },
  {
    "source": "computerfinearts",
    "source_url": "https://web.archive.org/web/20060222041059/http://www.computerfinearts.com/collection/nelson/ending15/",
    "title": "ending15",
    "artist": "Jason Nelson",
    "year": null,
    "url": "http://www.computerfinearts.com/collection/nelson/ending15/",
    "medium": "Net art"
  },
  {
    "source": "computerfinearts",
    "source_url": "https://web.archive.org/web/20061011045640/http://www.computerfinearts.com/collection/nelson/ending3/",
    "title": "ending3",
    "artist": "Jason Nelson",
    "year": null,
    "url": "http://www.computerfinearts.com/collection/nelson/ending3/",
    "medium": "Net art"
  },
  {
    "source": "computerfinearts",
    "source_url": "https://web.archive.org/web/20060222041053/http://www.computerfinearts.com/collection/nelson/ending4/",
    "title": "ending4",
    "artist": "Jason Nelson",
    "year": null,
    "url": "http://www.computerfinearts.com/collection/nelson/ending4/",
    "medium": "Net art"
  },
  {
    "source": "computerfinearts",
    "source_url": "https://web.archive.org/web/20060222041022/http://www.computerfinearts.com/collection/nelson/plush/",
    "title": "plush",
    "artist": "Jason Nelson",
    "year": null,
    "url": "http://www.computerfinearts.com/collection/nelson/plush/",
    "medium": "Net art"
  },
  {
    "source": "computerfinearts",
    "source_url": "https://web.archive.org/web/20061010092019/http://www.computerfinearts.com/collection/mcdonald/screenkiss/",
    "title": "ScreenKiss",
    "artist": "Jess McDonald",
    "year": null,
    "url": "http://www.computerfinearts.com/collection/mcdonald/screenkiss/",
    "medium": "Net art"
  },
  {
    "source": "computerfinearts",
    "source_url": "https://web.archive.org/web/20060212104419/http://www.computerfinearts.com/collection/andrews/",
    "title": "On Lionel Kearns (Home) by Jim Andrews",
    "artist": "Jim Andrews",
    "year": null,
    "url": "http://www.computerfinearts.com/collection/andrews/",
    "medium": "Net art"
  },
  {
    "source": "computerfinearts",
    "source_url": "https://web.archive.org/web/20060222030130/http://www.computerfinearts.com/collection/van_anden/ascii_chewy/",
    "title": "ascii chewy",
    "artist": "Jim Van Anden",
    "year": null,
    "url": "http://www.computerfinearts.com/collection/van_anden/ascii_chewy/",
    "medium": "Net art"
  },
  {
    "source": "computerfinearts",
    "source_url": "https://web.archive.org/web/20060222030112/http://www.computerfinearts.com/collection/van_anden/chewy_pack/",
    "title": "audience",
    "artist": "Jim Van Anden",
    "year": null,
    "url": "http://www.computerfinearts.com/collection/van_anden/chewy_pack/",
    "medium": "Net art"
  },
  {
    "source": "computerfinearts",
    "source_url": "https://web.archive.org/web/20070910003336/http://www.computerfinearts.com/collection/jimpunk/gLynch_N4/",
    "title": "gLynch N4",
    "artist": "jimpunk",
    "year": null,
    "url": "http://www.computerfinearts.com/collection/jimpunk/gLynch_N4/",
    "medium": "Net art"
  },
  {
    "source": "computerfinearts",
    "source_url": "https://web.archive.org/web/20060222025458/http://www.computerfinearts.com/collection/zellen/excerpt/",
    "title": "... ... ...",
    "artist": "Jody Zellen",
    "year": null,
    "url": "http://www.computerfinearts.com/collection/zellen/excerpt/",
    "medium": "Net art"
  },
  {
    "source": "computerfinearts",
    "source_url": "https://web.archive.org/web/20060222023736/http://www.computerfinearts.com/collection/zellen/war/",
    "title": "War",
    "artist": "Jody Zellen",
    "year": null,
    "url": "http://www.computerfinearts.com/collection/zellen/war/",
    "medium": "Net art"
  },
  {
    "source": "computerfinearts",
    "source_url": "https://web.archive.org/web/20060222024328/http://www.computerfinearts.com/collection/simon/9cons/",
    "title": "9Cons",
    "artist": "John F. Simon Jr.",
    "year": null,
    "url": "http://www.computerfinearts.com/collection/simon/9cons/",
    "medium": "Net art"
  },
  {
    "source": "computerfinearts",
    "source_url": "https://web.archive.org/web/20060222025543/http://www.computerfinearts.com/collection/simon/everyIcon/",
    "title": "Every Icon",
    "artist": "John F. Simon Jr.",
    "year": null,
    "url": "http://www.computerfinearts.com/collection/simon/everyIcon/",
    "medium": "Net art"
  },
  {
    "source": "computerfinearts",
    "source_url": "https://web.archive.org/web/20021020044505/http://www.computerfinearts.com/collection/klima/DF/",
    "title": "DF",
    "artist": "John Klima",
    "year": null,
    "url": "http://www.computerfinearts.com/collection/klima/DF/",
    "medium": "Net art"
  },
  {
    "source": "computerfinearts",
    "source_url": "https://web.archive.org/web/20060222030041/http://www.computerfinearts.com/collection/nechvatal/redattack/",
    "title": "RED OVOID ATTACK",
    "artist": "Joseph Nechvatal",
    "year": null,
    "url": "http://www.computerfinearts.com/collection/nechvatal/redattack/",
    "medium": "Net art"
  },
  {
    "source": "computerfinearts",
    "source_url": "https://web.archive.org/web/20060215041725/http://www.computerfinearts.com/collection/KRN/internautre/",
    "title": "Internautre",
    "artist": "KRN",
    "year": null,
    "url": "http://www.computerfinearts.com/collection/KRN/internautre/",
    "medium": "Net art"
  },
  {
    "source": "computerfinearts",
    "source_url": "https://web.archive.org/web/20060222031536/http://www.computerfinearts.com/collection/lacook%20-coming/echo/",
    "title": "Echo",
    "artist": "Lacook -Coming",
    "year": null,
    "url": "http://www.computerfinearts.com/collection/lacook%20-coming/echo/",
    "medium": "Net art"
  },
  {
    "source": "computerfinearts",
    "source_url": "https://web.archive.org/web/20060222031639/http://www.computerfinearts.com/collection/lacook%20-coming/entrails/",
    "title": "entrails",
    "artist": "Lacook -Coming",
    "year": null,
    "url": "http://www.computerfinearts.com/collection/lacook%20-coming/entrails/",
    "medium": "Net art"
  },
  {
    "source": "computerfinearts",
    "source_url": "https://web.archive.org/web/20060222031940/http://www.computerfinearts.com/collection/lacook%20-coming/metatelephony/",
    "title": "metatelephony-->Lewis LaCook",
    "artist": "Lacook -Coming",
    "year": null,
    "url": "http://www.computerfinearts.com/collection/lacook%20-coming/metatelephony/",
    "medium": "Net art"
  },
  {
    "source": "computerfinearts",
    "source_url": "https://web.archive.org/web/20070828081241/http://www.computerfinearts.com/collection/lacook/echo/",
    "title": "Echo",
    "artist": "Lance Lacook",
    "year": null,
    "url": "http://www.computerfinearts.com/collection/lacook/echo/",
    "medium": "Net art"
  },
  {
    "source": "computerfinearts",
    "source_url": "https://web.archive.org/web/20061208220749/http://www.computerfinearts.com/collection/lacook/entrails/",
    "title": "entrails",
    "artist": "Lance Lacook",
    "year": null,
    "url": "http://www.computerfinearts.com/collection/lacook/entrails/",
    "medium": "Net art"
  },
  {
    "source": "computerfinearts",
    "source_url": "https://web.archive.org/web/20070827220918/http://www.computerfinearts.com/collection/lacook/metatelephony/",
    "title": "metatelephony-->Lewis LaCook",
    "artist": "Lance Lacook",
    "year": null,
    "url": "http://www.computerfinearts.com/collection/lacook/metatelephony/",
    "medium": "Net art"
  },
  {
    "source": "computerfinearts",
    "source_url": "https://web.archive.org/web/20090127031022/http://www.computerfinearts.com/collection/leckey/",
    "title": "nydelivery.com design",
    "artist": "Leckey",
    "year": null,
    "url": "http://www.computerfinearts.com/collection/leckey/",
    "medium": "Net art"
  },
  {
    "source": "computerfinearts",
    "source_url": "https://web.archive.org/web/20060222022220/http://www.computerfinearts.com/collection/lia/10/",
    "title": "10",
    "artist": "Lia",
    "year": null,
    "url": "http://www.computerfinearts.com/collection/lia/10/",
    "medium": "Net art"
  },
  {
    "source": "computerfinearts",
    "source_url": "https://web.archive.org/web/20060222024622/http://www.computerfinearts.com/collection/jevbratt/ooo/",
    "title": "Out of the Ordinary",
    "artist": "Lisa Jevbratt",
    "year": null,
    "url": "http://www.computerfinearts.com/collection/jevbratt/ooo/",
    "medium": "Net art"
  },
  {
    "source": "computerfinearts",
    "source_url": "https://web.archive.org/web/20030924202738/http://www.computerfinearts.com/collection/lo_y/030404/",
    "title": "030404",
    "artist": "lo_y",
    "year": null,
    "url": "http://www.computerfinearts.com/collection/lo_y/030404/",
    "medium": "Net art"
  },
  {
    "source": "computerfinearts",
    "source_url": "https://web.archive.org/web/20061010090453/http://www.computerfinearts.com/collection/lokiss/has_had/",
    "title": "[--has/had--]",
    "artist": "Lokiss",
    "year": null,
    "url": "http://www.computerfinearts.com/collection/lokiss/has_had/",
    "medium": "Net art"
  },
  {
    "source": "computerfinearts",
    "source_url": "https://web.archive.org/web/20060222025713/http://www.computerfinearts.com/collection/lokiss/like_love/",
    "title": "[--like/love--]",
    "artist": "Lokiss",
    "year": null,
    "url": "http://www.computerfinearts.com/collection/lokiss/like_love/",
    "medium": "Net art"
  },
  {
    "source": "computerfinearts",
    "source_url": "https://web.archive.org/web/20060222025821/http://www.computerfinearts.com/collection/bravo/playingwtime/",
    "title": "M O N I K A B R A V O::: P LAYING WITH TIME",
    "artist": "Manik Bravo",
    "year": null,
    "url": "http://www.computerfinearts.com/collection/bravo/playingwtime/",
    "medium": "Net art"
  },
  {
    "source": "computerfinearts",
    "source_url": "https://web.archive.org/web/20061010091307/http://www.computerfinearts.com/collection/garrett/email_art/",
    "title": "++++marc 's_email_art++++",
    "artist": "Marc Garrett",
    "year": null,
    "url": "http://www.computerfinearts.com/collection/garrett/email_art/",
    "medium": "Net art"
  },
  {
    "source": "computerfinearts",
    "source_url": "https://web.archive.org/web/20060222025643/http://www.computerfinearts.com/collection/garrett/hardware/",
    "title": "Hardware",
    "artist": "Marc Garrett",
    "year": null,
    "url": "http://www.computerfinearts.com/collection/garrett/hardware/",
    "medium": "Net art"
  },
  {
    "source": "computerfinearts",
    "source_url": "https://web.archive.org/web/20060208162759/http://www.computerfinearts.com/collection/walczak/futureface/",
    "title": "futureface",
    "artist": "Marek Walczak",
    "year": null,
    "url": "http://www.computerfinearts.com/collection/walczak/futureface/",
    "medium": "Net art"
  },
  {
    "source": "computerfinearts",
    "source_url": "https://web.archive.org/web/20070827004907/http://www.computerfinearts.com/collection/zurkow/Hole_Fissure/",
    "title": "Hole & Fissure",
    "artist": "Marina Zurkow",
    "year": null,
    "url": "http://www.computerfinearts.com/collection/zurkow/Hole_Fissure/",
    "medium": "Net art"
  },
  {
    "source": "computerfinearts",
    "source_url": "https://web.archive.org/web/20061030085600/http://www.computerfinearts.com/collection/amerika/htc1.0/",
    "title": "Hypertextual Consciousness 1.0",
    "artist": "Mark Amerika",
    "year": null,
    "url": "http://www.computerfinearts.com/collection/amerika/htc1.0/",
    "medium": "Net art"
  },
  {
    "source": "computerfinearts",
    "source_url": "https://web.archive.org/web/20061030084410/http://www.computerfinearts.com/collection/lafia/memexengine/",
    "title": "Memex Engine",
    "artist": "Mark Lafia",
    "year": null,
    "url": "http://www.computerfinearts.com/collection/lafia/memexengine/",
    "medium": "Net art"
  },
  {
    "source": "computerfinearts",
    "source_url": "https://web.archive.org/web/20021020060447/http://www.computerfinearts.com/collection/napier/d-machine/",
    "title": "FEED",
    "artist": "Mark Napier",
    "year": null,
    "url": "http://www.computerfinearts.com/collection/napier/d-machine/",
    "medium": "Net art"
  },
  {
    "source": "computerfinearts",
    "source_url": "https://web.archive.org/web/20060222023634/http://www.computerfinearts.com/collection/napier/ekg/",
    "title": "FEED",
    "artist": "Mark Napier",
    "year": null,
    "url": "http://www.computerfinearts.com/collection/napier/ekg/",
    "medium": "Net art"
  },
  {
    "source": "computerfinearts",
    "source_url": "https://web.archive.org/web/20071101131901/http://www.computerfinearts.com/collection/napier/skywhite/",
    "title": "Skywhite",
    "artist": "Mark Napier",
    "year": null,
    "url": "http://www.computerfinearts.com/collection/napier/skywhite/",
    "medium": "Net art"
  },
  {
    "source": "computerfinearts",
    "source_url": "https://web.archive.org/web/20030219073907/http://www.computerfinearts.com/collection/tribe/revelation2/",
    "title": "Revelation 2.0",
    "artist": "Mark Tribe",
    "year": null,
    "url": "http://www.computerfinearts.com/collection/tribe/revelation2/",
    "medium": "Net art"
  },
  {
    "source": "computerfinearts",
    "source_url": "https://web.archive.org/web/20020108044757/http://www.computerfinearts.com/collection/wattenberg/livingmobile/",
    "title": "Living Mobile II",
    "artist": "Martin Wattenberg",
    "year": null,
    "url": "http://www.computerfinearts.com/collection/wattenberg/livingmobile/",
    "medium": "Net art"
  },
  {
    "source": "computerfinearts",
    "source_url": "https://web.archive.org/web/20060222024726/http://www.computerfinearts.com/collection/nakamura/bcc/",
    "title": "Bcc",
    "artist": "Masato Nakamura",
    "year": null,
    "url": "http://www.computerfinearts.com/collection/nakamura/bcc/",
    "medium": "Net art"
  },
  {
    "source": "computerfinearts",
    "source_url": "https://web.archive.org/web/20060222025829/http://www.computerfinearts.com/collection/daggett/referprint/",
    "title": "ReferPrint",
    "artist": "Matt Daggett",
    "year": null,
    "url": "http://www.computerfinearts.com/collection/daggett/referprint/",
    "medium": "Net art"
  },
  {
    "source": "computerfinearts",
    "source_url": "https://web.archive.org/web/20060126085917/http://www.computerfinearts.com/collection/rackham/aland/",
    "title": "+ aland +",
    "artist": "Melinda Rackham",
    "year": null,
    "url": "http://www.computerfinearts.com/collection/rackham/aland/",
    "medium": "Net art"
  },
  {
    "source": "computerfinearts",
    "source_url": "https://web.archive.org/web/20060222024732/http://www.computerfinearts.com/collection/rackham/line/",
    "title": "___line___",
    "artist": "Melinda Rackham",
    "year": null,
    "url": "http://www.computerfinearts.com/collection/rackham/line/",
    "medium": "Net art"
  },
  {
    "source": "computerfinearts",
    "source_url": "https://web.archive.org/web/20060222040943/http://www.computerfinearts.com/collection/breeze/PLT/",
    "title": "<.SNIP.>E",
    "artist": "Mez Breeze",
    "year": null,
    "url": "http://www.computerfinearts.com/collection/breeze/PLT/",
    "medium": "Net art"
  },
  {
    "source": "computerfinearts",
    "source_url": "https://web.archive.org/web/20080720060726/http://www.computerfinearts.com/collection/breeze/selectext/",
    "title": "][selec][text",
    "artist": "Mez Breeze",
    "year": null,
    "url": "http://www.computerfinearts.com/collection/breeze/selectext/",
    "medium": "Net art"
  },
  {
    "source": "computerfinearts",
    "source_url": "https://web.archive.org/web/20060222040958/http://www.computerfinearts.com/collection/breeze/SOM/",
    "title": "_][s][hut][ters][ of d.funct meat_//Shutters of Defunct Meat.",
    "artist": "Mez Breeze",
    "year": null,
    "url": "http://www.computerfinearts.com/collection/breeze/SOM/",
    "medium": "Net art"
  },
  {
    "source": "computerfinearts",
    "source_url": "https://web.archive.org/web/20060222041017/http://www.computerfinearts.com/collection/breeze/Re_ad/",
    "title": "Re ad",
    "artist": "Mez Breeze",
    "year": null,
    "url": "http://www.computerfinearts.com/collection/breeze/Re_ad/",
    "medium": "Net art"
  },
  {
    "source": "computerfinearts",
    "source_url": "https://web.archive.org/web/20060222041041/http://www.computerfinearts.com/collection/breeze/rictus/",
    "title": "Rictus",
    "artist": "Mez Breeze",
    "year": null,
    "url": "http://www.computerfinearts.com/collection/breeze/rictus/",
    "medium": "Net art"
  },
  {
    "source": "computerfinearts",
    "source_url": "https://web.archive.org/web/20030803060740/http://www.computerfinearts.com/collection/takeo/reconstruction/",
    "title": "reconstruction",
    "artist": "Michael Takeo Magruder",
    "year": null,
    "url": "http://www.computerfinearts.com/collection/takeo/reconstruction/",
    "medium": "Net art"
  },
  {
    "source": "computerfinearts",
    "source_url": "https://web.archive.org/web/20050728122019/http://www.computerfinearts.com/collection/szpakowski/3movies/",
    "title": "three movies",
    "artist": "Michal Szpakowski",
    "year": null,
    "url": "http://www.computerfinearts.com/collection/szpakowski/3movies/",
    "medium": "Net art"
  },
  {
    "source": "computerfinearts",
    "source_url": "https://web.archive.org/web/20060707192133/http://www.computerfinearts.com/collection/mig/loopixel/",
    "title": "Loopixel",
    "artist": "Mig",
    "year": null,
    "url": "http://www.computerfinearts.com/collection/mig/loopixel/",
    "medium": "Net art"
  },
  {
    "source": "computerfinearts",
    "source_url": "https://web.archive.org/web/20060222025910/http://www.computerfinearts.com/collection/mouchette/m.org.ue/",
    "title": "M.Org.Ue",
    "artist": "Mouchette",
    "year": null,
    "url": "http://www.computerfinearts.com/collection/mouchette/m.org.ue/",
    "medium": "Net art"
  },
  {
    "source": "computerfinearts",
    "source_url": "https://web.archive.org/web/20021219075318/http://www.computerfinearts.com/collection/mouchette/filmxx/",
    "title": "||| My Quiz |||",
    "artist": "Mouchette",
    "year": null,
    "url": "http://www.computerfinearts.com/collection/mouchette/filmxx/",
    "medium": "Net art"
  },
  {
    "source": "computerfinearts",
    "source_url": "https://web.archive.org/web/20031018115852/http://www.computerfinearts.com/collection/MTAA/websiteunseen1/",
    "title": "Random Access Mortality",
    "artist": "MTAA",
    "year": null,
    "url": "http://www.computerfinearts.com/collection/MTAA/websiteunseen1/",
    "medium": "Net art"
  },
  {
    "source": "computerfinearts",
    "source_url": "https://web.archive.org/web/20061010085434/http://www.computerfinearts.com/collection/stern/hektor/",
    "title": "hektor",
    "artist": "Nathaniel Stern",
    "year": null,
    "url": "http://www.computerfinearts.com/collection/stern/hektor/",
    "medium": "Net art"
  },
  {
    "source": "computerfinearts",
    "source_url": "https://web.archive.org/web/20060222024454/http://www.computerfinearts.com/collection/clauss/lecri/",
    "title": "nicolas clauss",
    "artist": "Nicolas Clauss",
    "year": null,
    "url": "http://www.computerfinearts.com/collection/clauss/lecri/",
    "medium": "Net art"
  },
  {
    "source": "computerfinearts",
    "source_url": "https://web.archive.org/web/20070205002914/http://www.computerfinearts.com/collection/clauss/scalpel/",
    "title": "nicolas clauss",
    "artist": "Nicolas Clauss",
    "year": null,
    "url": "http://www.computerfinearts.com/collection/clauss/scalpel/",
    "medium": "Net art"
  },
  {
    "source": "computerfinearts",
    "source_url": "https://web.archive.org/web/20060222025904/http://www.computerfinearts.com/collection/lialina/stellastar/",
    "title": "The most beautiful web page",
    "artist": "Olia Lialina",
    "year": null,
    "url": "http://www.computerfinearts.com/collection/lialina/stellastar/",
    "medium": "Net art"
  },
  {
    "source": "computerfinearts",
    "source_url": "https://web.archive.org/web/20061010092006/http://www.computerfinearts.com/collection/lichty/assoniations/",
    "title": "intro",
    "artist": "Patrick Lichty",
    "year": null,
    "url": "http://www.computerfinearts.com/collection/lichty/assoniations/",
    "medium": "Net art"
  },
  {
    "source": "computerfinearts",
    "source_url": "https://web.archive.org/web/20060222024941/http://www.computerfinearts.com/collection/lichty/sprawl/",
    "title": "Sprawl",
    "artist": "Patrick Lichty",
    "year": null,
    "url": "http://www.computerfinearts.com/collection/lichty/sprawl/",
    "medium": "Net art"
  },
  {
    "source": "computerfinearts",
    "source_url": "https://web.archive.org/web/20060222070516/http://www.computerfinearts.com/collection/wood/summer-2004/",
    "title": "sabbatical",
    "artist": "Paul Wood",
    "year": null,
    "url": "http://www.computerfinearts.com/collection/wood/summer-2004/",
    "medium": "Net art"
  },
  {
    "source": "computerfinearts",
    "source_url": "https://web.archive.org/web/20031004201106/http://www.computerfinearts.com/collection/pavu/r0unDback/",
    "title": "r0un Db ack",
    "artist": "pavu.com",
    "year": null,
    "url": "http://www.computerfinearts.com/collection/pavu/r0unDback/",
    "medium": "Net art"
  },
  {
    "source": "computerfinearts",
    "source_url": "https://web.archive.org/web/20050718082740/http://www.computerfinearts.com/collection/horvath/uloho/",
    "title": "Unexpected Launching of Heavy Objects",
    "artist": "Peter Horvath",
    "year": null,
    "url": "http://www.computerfinearts.com/collection/horvath/uloho/",
    "medium": "Net art"
  },
  {
    "source": "computerfinearts",
    "source_url": "https://web.archive.org/web/20040103145923/http://www.computerfinearts.com/collection/luining/doktertje_spelen/",
    "title": "ctrlaltdel-----> Doktertje Spelen",
    "artist": "Peter Luining",
    "year": null,
    "url": "http://www.computerfinearts.com/collection/luining/doktertje_spelen/",
    "medium": "Net art"
  },
  {
    "source": "computerfinearts",
    "source_url": "https://web.archive.org/web/20060222030144/http://www.computerfinearts.com/collection/luining/PreTTy_CenSorED/",
    "title": "ctrlaltdel-----> Pretty CenSorED",
    "artist": "Peter Luining",
    "year": null,
    "url": "http://www.computerfinearts.com/collection/luining/PreTTy_CenSorED/",
    "medium": "Net art"
  },
  {
    "source": "computerfinearts",
    "source_url": "https://web.archive.org/web/20060212104840/http://www.computerfinearts.com/collection/packer/ep/",
    "title": "Experimental Party DisInformation Center",
    "artist": "Randall Packer",
    "year": null,
    "url": "http://www.computerfinearts.com/collection/packer/ep/",
    "medium": "Net art"
  },
  {
    "source": "computerfinearts",
    "source_url": "https://web.archive.org/web/20060222031117/http://www.computerfinearts.com/collection/drouhin/ici/",
    "title": "!C! . 2002 . Reynald Drouhin",
    "artist": "Reynald Drouhin",
    "year": null,
    "url": "http://www.computerfinearts.com/collection/drouhin/ici/",
    "medium": "Net art"
  },
  {
    "source": "computerfinearts",
    "source_url": "https://web.archive.org/web/20060222031411/http://www.computerfinearts.com/collection/drouhin/j-eux/",
    "title": "J'eux . 2001 . Reynald Drouhin",
    "artist": "Reynald Drouhin",
    "year": null,
    "url": "http://www.computerfinearts.com/collection/drouhin/j-eux/",
    "medium": "Net art"
  },
  {
    "source": "computerfinearts",
    "source_url": "https://web.archive.org/web/20060222031216/http://www.computerfinearts.com/collection/drouhin/om/",
    "title": "Om . 2001 . Reynald Drouhin",
    "artist": "Reynald Drouhin",
    "year": null,
    "url": "http://www.computerfinearts.com/collection/drouhin/om/",
    "medium": "Net art"
  },
  {
    "source": "computerfinearts",
    "source_url": "https://web.archive.org/web/20060212104950/http://www.computerfinearts.com/collection/RSG/RSG-CPE0C-1/",
    "title": "RSG-CPE0C-1",
    "artist": "RSG (Radical Software Group)",
    "year": null,
    "url": "http://www.computerfinearts.com/collection/RSG/RSG-CPE0C-1/",
    "medium": "Net art"
  },
  {
    "source": "computerfinearts",
    "source_url": "https://web.archive.org/web/20040711175311/http://www.computerfinearts.com/collection/cheang/stop/",
    "title": "stop",
    "artist": "Shu Lea Cheang",
    "year": null,
    "url": "http://www.computerfinearts.com/collection/cheang/stop/",
    "medium": "Net art"
  },
  {
    "source": "computerfinearts",
    "source_url": "https://web.archive.org/web/20060222024744/http://www.computerfinearts.com/collection/biggs/echelon/",
    "title": "Echelon",
    "artist": "Simon Biggs",
    "year": null,
    "url": "http://www.computerfinearts.com/collection/biggs/echelon/",
    "medium": "Net art"
  },
  {
    "source": "computerfinearts",
    "source_url": "https://web.archive.org/web/20060222024738/http://www.computerfinearts.com/collection/ahn/inbetween/",
    "title": "inbetween",
    "artist": "Sun-Young Ahn",
    "year": null,
    "url": "http://www.computerfinearts.com/collection/ahn/inbetween/",
    "medium": "Net art"
  },
  {
    "source": "computerfinearts",
    "source_url": "https://web.archive.org/web/20080515092912/http://www.computerfinearts.com/collection/lai/no_future/",
    "title": "no_future",
    "artist": "Tamara Lai",
    "year": null,
    "url": "http://www.computerfinearts.com/collection/lai/no_future/",
    "medium": "Net art"
  },
  {
    "source": "computerfinearts",
    "source_url": "https://web.archive.org/web/20060222025519/http://www.computerfinearts.com/collection/lai/web_of_lies/",
    "title": "Web of lies / Tamara La\u00ef",
    "artist": "Tamara Lai",
    "year": null,
    "url": "http://www.computerfinearts.com/collection/lai/web_of_lies/",
    "medium": "Net art"
  },
  {
    "source": "computerfinearts",
    "source_url": "https://web.archive.org/web/20060222031609/http://www.computerfinearts.com/collection/thomson_craighead/cnn/",
    "title": "Thomson & Craighead",
    "artist": "Thomson & Craighead",
    "year": null,
    "url": "http://www.computerfinearts.com/collection/thomson_craighead/cnn/",
    "medium": "Net art"
  },
  {
    "source": "computerfinearts",
    "source_url": "https://web.archive.org/web/20060222031530/http://www.computerfinearts.com/collection/thomson_craighead/th/",
    "title": "Trigger Happy. Thomson & Craighead.",
    "artist": "Thomson & Craighead",
    "year": null,
    "url": "http://www.computerfinearts.com/collection/thomson_craighead/th/",
    "medium": "Net art"
  },
  {
    "source": "computerfinearts",
    "source_url": "https://web.archive.org/web/20060222031946/http://www.computerfinearts.com/collection/thomson_craighead/weather_gauge/",
    "title": "Weather Gauge",
    "artist": "Thomson & Craighead",
    "year": null,
    "url": "http://www.computerfinearts.com/collection/thomson_craighead/weather_gauge/",
    "medium": "Net art"
  },
  {
    "source": "computerfinearts",
    "source_url": "https://web.archive.org/web/20060222031623/http://www.computerfinearts.com/collection/thomson_craighead/beacon/",
    "title": "automated_beacon",
    "artist": "Thomson & Craighead",
    "year": null,
    "url": "http://www.computerfinearts.com/collection/thomson_craighead/beacon/",
    "medium": "Net art"
  },
  {
    "source": "computerfinearts",
    "source_url": "https://web.archive.org/web/20030405113634/http://www.computerfinearts.com/collection/laporta/distance/",
    "title": "Tina LaPorta: Distance",
    "artist": "Tina LaPorta",
    "year": null,
    "url": "http://www.computerfinearts.com/collection/laporta/distance/",
    "medium": "Net art"
  },
  {
    "source": "computerfinearts",
    "source_url": "https://web.archive.org/web/20051201102912/http://www.computerfinearts.com/collection/utensil/1+1/",
    "title": "1 + 1 by Beth Stryker + Sawad Brooks",
    "artist": "Utensil",
    "year": null,
    "url": "http://www.computerfinearts.com/collection/utensil/1+1/",
    "medium": "Net art"
  },
  {
    "source": "computerfinearts",
    "source_url": "https://web.archive.org/web/20070824005116/http://www.computerfinearts.com/collection/grancher/googlealphabet/",
    "title": "Google alphabet",
    "artist": "Valery Grancher",
    "year": null,
    "url": "http://www.computerfinearts.com/collection/grancher/googlealphabet/",
    "medium": "Net art"
  },
  {
    "source": "computerfinearts",
    "source_url": "https://web.archive.org/web/20070824005231/http://www.computerfinearts.com/collection/grancher/googlenumbers/",
    "title": "Google alphabet",
    "artist": "Valery Grancher",
    "year": null,
    "url": "http://www.computerfinearts.com/collection/grancher/googlenumbers/",
    "medium": "Net art"
  },
  {
    "source": "computerfinearts",
    "source_url": "https://web.archive.org/web/20070824170957/http://www.computerfinearts.com/collection/grancher/googlepainting/",
    "title": "Google Painting. Oil on canvas 2001",
    "artist": "Valery Grancher",
    "year": null,
    "url": "http://www.computerfinearts.com/collection/grancher/googlepainting/",
    "medium": "Net art"
  },
  {
    "source": "computerfinearts",
    "source_url": "https://web.archive.org/web/20030219121741/http://www.computerfinearts.com/collection/grancher/jerusalem/",
    "title": "jerusalem",
    "artist": "Valery Grancher",
    "year": null,
    "url": "http://www.computerfinearts.com/collection/grancher/jerusalem/",
    "medium": "Net art"
  },
  {
    "source": "computerfinearts",
    "source_url": "https://web.archive.org/web/20070828212657/http://www.computerfinearts.com/collection/grancher/selfportrait/",
    "title": "Selfportrait",
    "artist": "Valery Grancher",
    "year": null,
    "url": "http://www.computerfinearts.com/collection/grancher/selfportrait/",
    "medium": "Net art"
  },
  {
    "source": "computerfinearts",
    "source_url": "https://web.archive.org/web/20070830180639/http://www.computerfinearts.com/collection/cahen/03_20/",
    "title": "03 20",
    "artist": "Xavier Cahen",
    "year": null,
    "url": "http://www.computerfinearts.com/collection/cahen/03_20/",
    "medium": "Net art"
  },
  {
    "source": "computerfinearts",
    "source_url": "https://web.archive.org/web/20060222030118/http://www.computerfinearts.com/collection/cahen/louvre_01_15_05/",
    "title": "Le Louvre, rassemblement pour la gratuit\u00e9.",
    "artist": "Xavier Cahen",
    "year": null,
    "url": "http://www.computerfinearts.com/collection/cahen/louvre_01_15_05/",
    "medium": "Net art"
  },
  {
    "source": "computerfinearts",
    "source_url": "https://web.archive.org/web/20060222030124/http://www.computerfinearts.com/collection/kanarek/extremebeauty/",
    "title": "World of Awe: Extreme Beauty",
    "artist": "Yael Kanarek",
    "year": null,
    "url": "http://www.computerfinearts.com/collection/kanarek/extremebeauty/",
    "medium": "Net art"
  },
  {
    "source": "computerfinearts",
    "source_url": "https://web.archive.org/web/20021021085518/http://www.computerfinearts.com/collection/kanarek/hello/",
    "title": "World of Awe: Hello",
    "artist": "Yael Kanarek",
    "year": null,
    "url": "http://www.computerfinearts.com/collection/kanarek/hello/",
    "medium": "Net art"
  },
  {
    "source": "computerfinearts",
    "source_url": "https://web.archive.org/web/20060222025924/http://www.computerfinearts.com/collection/sodeoka/ascii_rock/",
    "title": "Ascii Rock",
    "artist": "Yoshi Sodeoka",
    "year": null,
    "url": "http://www.computerfinearts.com/collection/sodeoka/ascii_rock/",
    "medium": "Net art"
  },
  {
    "source": "computerfinearts",
    "source_url": "https://web.archive.org/web/20020815165716/http://www.computerfinearts.com/collection/YOUNG_HAE_CHANG_HEAVY_INDUSTRIES/FROM_SEOUL_LAND/",
    "title": "FROM SEOUL LAND",
    "artist": "Young-Hae Chang Heavy Industries",
    "year": null,
    "url": "http://www.computerfinearts.com/collection/YOUNG_HAE_CHANG_HEAVY_INDUSTRIES/FROM_SEOUL_LAND/",
    "medium": "Net art"
  },
  {
    "source": "computerfinearts",
    "source_url": "https://web.archive.org/web/20061010091822/http://www.computerfinearts.com/collection/zhang/etant_donnes/",
    "title": "etant donn\u00e9s",
    "artist": "Zhang Ga",
    "year": null,
    "url": "http://www.computerfinearts.com/collection/zhang/etant_donnes/",
    "medium": "Net art"
  }
]